[
  {
    "id": "7c617efe-cc81-4ae4-9dd6-a51c22cdb9c4",
    "isVerified": false,
    "email": "frtocco@gmail.com",
    "password": "$2b$10$wrxjBDmojU5m38JHW9Cpier3ah/lZ6BsxKxWG4qoFMFnPIcKQUSXq",
    "username": "Frtocco"
  },
  {
    "id": "364b34b5-73cb-484f-a375-e4ca56d4d6ea",
    "isVerified": false,
    "email": "asd@gmail.com",
    "password": "$2b$10$Mqm7.YJenM/Da3fOqA9Ha.S0J3FZO7Zj7dnrh6YVUQOidXyFba76q",
    "username": "Frtocco1"
  },
  {
    "id": "9e8c7eb9-aaaa-4c2b-900a-5110d3a4a470",
    "isVerified": false,
    "email": "frantocco7@gmail.com",
    "password": "$2b$10$2Lah3MjVeFxnZKTE8cXTi.QpFZULfQVs./sGgY85LJ4jBYV8HWM5K",
    "username": "admin21"
  },
  {
    "id": "efb79b83-3856-4524-a149-29b3ac4184a0",
    "isVerified": false,
    "email": "frtocco12@gmail.com",
    "password": "$2b$10$8W2N3.tFDjF/zRrAB5EbH.SRIeWPng2YnGiSPvuRxugc.NjxfY6NS",
    "username": "Frtocco12"
  },
  {
    "id": "4ebf5c39-7e71-4e6f-98c7-3aafa37b9171",
    "isVerified": true,
    "email": "KIMCRIS00817@gmail.com",
    "password": "$2b$10$4/U1ow2IlwVMKePtKYsWEOkYs7dVhOQ4lLbTJO7mITRwFnav7BK5C",
    "username": "avocado",
    "resetToken": "8b776783-da88-4f00-8399-438deefc76b2",
    "resetTokenExpiry": 1745328198962
  },
  {
    "id": "67bd13d1-ee9b-4780-b4a5-486bcc871753",
    "isVerified": true,
    "email": "aguscastino01@gmail.com",
    "password": "$2b$10$lOhwrCM9LplCxuaTERhi8OP.Qw7YLOMNq52pIYppVUjIflTXhq1P6",
    "username": "agus"
  },
  {
    "id": "c7501d98-ef08-47ec-8e59-c4e9ae110eda",
    "isVerified": true,
    "email": "pedro@gmail.com",
    "password": "$2b$10$ncq6ZJjC2fzZYOS0I6eFrelFifj40t8AwadK.q1fQGprsd89FUEmC",
    "username": "pedro"
  },
  {
    "id": "08ccc0f6-8629-442d-9798-c5bbf314ca02",
    "isVerified": false,
    "email": "deremate764@gmail.com",
    "password": "$2b$10$tkwKjhHKAHnHtNJ52JmAAOMF6ylR/yl76SaOUJ7e2fpAE.umBbA2e",
    "username": "avocadoadmin"
  },
  {
    "id": "3105b5f4-0e95-474d-b6cb-693a4e0c17e7",
    "isVerified": false,
    "email": "frtocco24@gmail.com",
    "password": "$2b$10$XEK7NeaBGbuMbnnPpgmw0u6F3L9K/aTsnEQAq58rcuiNj8rkUhif.",
    "username": "Frtocco24"
  }
]